dromi/__init__.py
laedingr-0.0.1.dist-info/LICENSE.md
laedingr-0.0.1.dist-info/METADATA
laedingr-0.0.1.dist-info/WHEEL
laedingr-0.0.1.dist-info/top_level.txt
laedingr-0.0.1.dist-info/RECORD
